{"trial_id": "0019", "hyperparameters": {"space": [{"class_name": "Choice", "config": {"name": "activation", "default": "relu", "conditions": [], "values": ["relu", "tanh", "sigmoid"], "ordered": false}}, {"class_name": "Int", "config": {"name": "first_units", "default": null, "conditions": [], "min_value": 1, "max_value": 40, "step": 1, "sampling": "linear"}}, {"class_name": "Int", "config": {"name": "num_layers", "default": null, "conditions": [], "min_value": 1, "max_value": 6, "step": 1, "sampling": "linear"}}, {"class_name": "Int", "config": {"name": "units_0", "default": null, "conditions": [], "min_value": 1, "max_value": 40, "step": 1, "sampling": "linear"}}, {"class_name": "Int", "config": {"name": "units_1", "default": null, "conditions": [], "min_value": 1, "max_value": 40, "step": 1, "sampling": "linear"}}, {"class_name": "Int", "config": {"name": "units_2", "default": null, "conditions": [], "min_value": 1, "max_value": 40, "step": 1, "sampling": "linear"}}, {"class_name": "Int", "config": {"name": "units_3", "default": null, "conditions": [], "min_value": 1, "max_value": 40, "step": 1, "sampling": "linear"}}, {"class_name": "Int", "config": {"name": "units_4", "default": null, "conditions": [], "min_value": 1, "max_value": 40, "step": 1, "sampling": "linear"}}, {"class_name": "Int", "config": {"name": "units_5", "default": null, "conditions": [], "min_value": 1, "max_value": 40, "step": 1, "sampling": "linear"}}], "values": {"activation": "tanh", "first_units": 21, "num_layers": 3, "units_0": 16, "units_1": 11, "units_2": 25, "units_3": 28, "units_4": 27, "units_5": 1, "tuner/epochs": 2, "tuner/initial_epoch": 0, "tuner/bracket": 4, "tuner/round": 0}}, "metrics": {"metrics": {"accuracy": {"direction": "max", "observations": [{"value": [0.6898550987243652], "step": 1}]}, "loss": {"direction": "min", "observations": [{"value": [0.6134046912193298], "step": 1}]}, "val_accuracy": {"direction": "max", "observations": [{"value": [0.5478261113166809], "step": 1}]}, "val_loss": {"direction": "min", "observations": [{"value": [0.6878636479377747], "step": 1}]}}}, "score": 0.5478261113166809, "best_step": 1, "status": "COMPLETED", "message": null}